{
  "imports": {
    "/ts/ResourceLoader.": "/src/scripts/ts/ResourceLoader..ts",
    "/ts/ResourceLoader.types": "/src/scripts/ts/ResourceLoader.types.ts",
    "/ts/common/MetaTurple": "/src/scripts/ts/common/MetaTurple.ts",
    "/ts/common/datas": "/src/scripts/ts/common/datas.ts",
    "/ts/common/evalTypes": "/src/scripts/ts/common/evalTypes.ts",
    "/ts/common/generic": "/src/scripts/ts/common/generic.ts",
    "/ts/common/interfaces": "/src/scripts/ts/common/interfaces.ts",
    "/ts/common/numbers": "/src/scripts/ts/common/numbers.ts",
    "/ts/common/params": "/src/scripts/ts/common/params.ts",
    "/ts/credito/pj/SAC": "/src/scripts/ts/credito/pj/SAC.ts",
    "/ts/credito/pj/credito": "/src/scripts/ts/credito/pj/credito.ts",
    "/tsx/main": "/src/scrtips/tsx/main.tsx",
    "/tsx/main/Footer": "/src/scrtips/tsx/main/Footer.tsx",
    "/tsx/main/HeaderMain": "/src/scrtips/tsx/main/HeaderMain.tsx",
    "/tsx/main/HeaderSec": "/src/scrtips/tsx/main/HeaderSec.tsx",
    "/tsx/main/HeaderSectionTop": "/src/scrtips/tsx/main/HeaderSectionTop.tsx",
    "/tsx/main/HeaderTer": "/src/scrtips/tsx/main/HeaderTer.tsx",
    "/tsx/main/HeaderUpper": "/src/scrtips/tsx/main/HeaderUpper.tsx",
    "/tsx/main/MainContent": "/src/scrtips/tsx/main/MainContent.tsx",
    "/tsx/main/SectionAppWrapper": "/src/scrtips/tsx/main/SectionAppWrapper.tsx",
    "/tsx/main/SectionWrapper": "/src/scrtips/tsx/main/SectionWrapper.tsx"
  }
}